{
	"info": {
		"_postman_id": "0243f7a8-2e77-48bd-862c-7c42d21c0578",
		"name": "eos.uptrade.testaufgabe",
		"schema": "https://schema.getpostman.com/json/collection/v2.1.0/collection.json"
	},
	"item": [
		{
			"name": "Create User",
			"request": {
				"method": "POST",
				"header": [],
				"body": {
					"mode": "raw",
					"raw": "{\n    \"username\": \"Moh.Kaaaa\",\n    \"email\": \"moh@test.com\"\n}",
					"options": {
						"raw": {
							"language": "json"
						}
					}
				},
				"url": {
					"raw": "{{baseUrl}}/api/v1/users",
					"host": [
						"{{baseUrl}}"
					],
					"path": [
						"api",
						"v1",
						"users"
					]
				}
			},
			"response": []
		},
		{
			"name": "Update User",
			"request": {
				"method": "PUT",
				"header": [],
				"body": {
					"mode": "raw",
					"raw": "{\n    \"id\": 1,\n    \"username\": \"Moh.JSON haha\",\n    \"email\": \"moh@aaaaa.com\"\n}",
					"options": {
						"raw": {
							"language": "json"
						}
					}
				},
				"url": {
					"raw": "{{baseUrl}}/api/v1/users",
					"host": [
						"{{baseUrl}}"
					],
					"path": [
						"api",
						"v1",
						"users"
					]
				}
			},
			"response": []
		},
		{
			"name": "Get User",
			"request": {
				"method": "GET",
				"header": [],
				"url": {
					"raw": "{{baseUrl}}/api/v1/users/1",
					"host": [
						"{{baseUrl}}"
					],
					"path": [
						"api",
						"v1",
						"users",
						"1"
					]
				}
			},
			"response": []
		},
		{
			"name": "Get Users",
			"request": {
				"method": "GET",
				"header": []
			},
			"response": []
		},
		{
			"name": "Delete User",
			"request": {
				"method": "DELETE",
				"header": [],
				"body": {
					"mode": "raw",
					"raw": "{\n    \"id\": 14\n}"
				},
				"url": {
					"raw": "{{baseUrl}}/api/v1/users",
					"host": [
						"{{baseUrl}}"
					],
					"path": [
						"api",
						"v1",
						"users"
					]
				}
			},
			"response": []
		}
	],
	"event": [
		{
			"listen": "prerequest",
			"script": {
				"type": "text/javascript",
				"exec": [
					""
				]
			}
		},
		{
			"listen": "test",
			"script": {
				"type": "text/javascript",
				"exec": [
					""
				]
			}
		}
	],
	"variable": [
		{
			"key": "baseURL",
			"value": "http://127.0.0.1:8000",
			"type": "string"
		},
		{
			"key": "baseUrl",
			"value": "http://127.0.0.1:8000"
		}
	]
}